env_config/__init__.py
env_config/aws.py
env_config/cli.py
env_config/config.py
env_config/core.py
env_config/utils.py
env_config/version.py
env_config/shells/init.bash
env_config/shells/init.fish
env_config_cli-0.20250626.2.dist-info/METADATA
env_config_cli-0.20250626.2.dist-info/WHEEL
env_config_cli-0.20250626.2.dist-info/entry_points.txt
env_config_cli-0.20250626.2.dist-info/RECORD
