Metadata-Version: 2.4
Name: env-config-cli
Version: 0.20250626.2
Author-email: Randy Syring <randy.syring@level12.io>
Requires-Python: ~=3.12.0
Requires-Dist: boto3>=1.38.44
Requires-Dist: click>=8.2.1
Requires-Dist: cryptography>=45.0.4
Requires-Dist: dynamic-yaml>=2.0.0
Requires-Dist: furl>=2.1.4
Requires-Dist: msgpack>=1.1.1
Requires-Dist: pyserde>=0.24.0
